mindtrace/ui/__init__.py
mindtrace_ui-0.8.0.dist-info/licenses/LICENSE
mindtrace_ui-0.8.0.dist-info/METADATA
mindtrace_ui-0.8.0.dist-info/WHEEL
mindtrace_ui-0.8.0.dist-info/top_level.txt
mindtrace_ui-0.8.0.dist-info/RECORD
